LICENSE
shoonyapy/__init__.py
shoonyapy/shoonyapy.py
shoonyapy-0.1.1.dist-info/LICENSE
shoonyapy-0.1.1.dist-info/WHEEL
shoonyapy-0.1.1.dist-info/METADATA
shoonyapy-0.1.1.dist-info/RECORD
