Metadata-Version: 2.1
Name: shoonyapy
Version: 0.1.1
Summary: Unofficial Python wrapper for Trading REST APIs for Finvasia Shoonya platform
Home-page: https://gitlab.com/algo2t/shoonyapy
License: GPLv3
Author: Algo 2 Trade
Author-email: help@algo2.trade
Requires-Python: >=3.9,<4.0
Classifier: License :: Other/Proprietary License
Classifier: Programming Language :: Python :: 3
Classifier: Programming Language :: Python :: 3.9
Requires-Dist: getmac (>=0.8.2,<0.9.0)
Requires-Dist: pandas (>=1.3.1,<2.0.0)
Requires-Dist: requests (>=2.26.0,<3.0.0)
Project-URL: Repository, https://gitlab.com/algo2t/shoonyapy.git
